rfc_http_validate/__init__.py
rfc_http_validate/markdown.py
rfc_http_validate/methods.py
rfc_http_validate/ui.py
rfc_http_validate/validate.py
rfc_http_validate/xml.py
rfc_http_validate-0.3.4.dist-info/LICENSE.md
rfc_http_validate-0.3.4.dist-info/METADATA
rfc_http_validate-0.3.4.dist-info/WHEEL
rfc_http_validate-0.3.4.dist-info/entry_points.txt
rfc_http_validate-0.3.4.dist-info/top_level.txt
rfc_http_validate-0.3.4.dist-info/RECORD
