Metadata-Version: 2.1
Name: rfc-http-validate
Version: 0.3.4
Summary: DESCRIPTION
Author-email: Mark Nottingham <mnot@mnot.net>
License: Copyright (c) 2020 Mark Nottingham
Project-URL: homepage, https://github.com/mnot/rfc-http-validate/
Classifier: Operating System :: OS Independent
Classifier: Development Status :: 4 - Beta
Classifier: License :: OSI Approved :: MIT License
Requires-Python: >=3.9
License-File: LICENSE.md
Requires-Dist: http-sf >=1.0.1
Requires-Dist: blessings
Requires-Dist: commonmark
Provides-Extra: dev
Requires-Dist: mypy ; extra == 'dev'
Requires-Dist: black ; extra == 'dev'
Requires-Dist: pylint ; extra == 'dev'
Requires-Dist: pytest ; extra == 'dev'
Requires-Dist: pytest-md ; extra == 'dev'
Requires-Dist: validate-pyproject ; extra == 'dev'
Requires-Dist: build ; extra == 'dev'
Requires-Dist: types-commonmark ; extra == 'dev'
